[
{"albumcategory":"wedding","photo":"http://www.shivuweddingphotography.com/uploads/albumcover/_MG_1620.jpg","captions":"Couples Secret Talk","album": "couples"},
{"albumcategory":"wedding","photo":"http://www.shivuweddingphotography.com/uploads/albumcover/Im1%20(16).jpg","captions":"Impana - Vivek","album": "impana"},
  {"albumcategory":"wedding","photo":"http://www.shivuweddingphotography.com/uploads/albumcover/chethan(19).jpg","captions":"Chethan - Andria","album": "andria"},
  {"albumcategory":"wedding","photo":"http://www.shivuweddingphotography.com/uploads/albumcover/prachi001(18).jpg","captions":"Prachi - Abhay","album": "prachi"},
  {"albumcategory":"wedding","photo":"http://www.shivuweddingphotography.com/uploads/albumcover/r1%20(1).jpg","captions":"Rajeshwari - Praveen","album": "raji"},
  {"albumcategory":"wedding","photo":"http://www.shivuweddingphotography.com/uploads/albumcover/sanjal(3).jpg","captions":"Sanjal - Vikas","album": "sanjal"},
  {"albumcategory":"wedding","photo":"http://www.shivuweddingphotography.com/uploads/albumcover/za.jpg","captions":"Prasad - Mamatha","album": "prasad"},
  {"albumcategory":"wedding","photo":"http://www.shivuweddingphotography.com/uploads/albumcover/0005.jpg","captions":"Madhu - Vinaya","album": "madhu"},
  {"albumcategory":"wedding","photo":"http://www.shivuweddingphotography.com/uploads/albumcover/_MG_2419.jpg","captions":"Brides like baby","album": "bridesbaby"},
  {"albumcategory":"wedding","photo":"http://www.shivuweddingphotography.com/uploads/albumcover/002.jpg","captions":"Akshate in wedding","album": "akshathe"},
  {"albumcategory":"wedding","photo":"http://www.shivuweddingphotography.com/uploads/albumcover/IMG_2805.jpg","captions":"Dharshana - Pavan","album": "dharshana"},
  {"albumcategory":"wedding","photo":"http://www.shivuweddingphotography.com/uploads/albumcover/031.jpg","captions":"Megha - Kunal","album": "kunal"},
  {"albumcategory":"wedding","photo":"http://www.shivuweddingphotography.com/uploads/albumcover/1.jpg","captions":"Namratha - Navin","album": "namratha"},
  {"albumcategory":"wedding","photo":"http://www.shivuweddingphotography.com/uploads/albumcover/img_4772.jpg","captions":"Akash - Deepika(Belgaum)","album": "akash"},
  {"albumcategory":"wedding","photo":"http://www.shivuweddingphotography.com/uploads/albumcover/JE0A9170.jpg","captions":"Ashwini - Santhosh","album": "ashwini"},
  {"albumcategory":"wedding","photo":"http://www.shivuweddingphotography.com/uploads/albumcover/10.jpg","captions":"Athul - Smitha","album": "athul"},
  {"albumcategory":"wedding","photo":"http://www.shivuweddingphotography.com/uploads/albumcover/MCKL2389.jpg","captions":"Divya - Harsha","album": "harsha"},
  {"albumcategory":"wedding","photo":"http://www.shivuweddingphotography.com/uploads/albumcover/IMG_2387.jpg","captions":"Jagan - Abhinaya","album": "jagan"},
  {"albumcategory":"wedding","photo":"http://www.shivuweddingphotography.com/uploads/albumcover/001.jpg","captions":"Santhu - Deepa","album": "santhudeepa"},
  {"albumcategory":"wedding","photo":"http://www.shivuweddingphotography.com/uploads/albumcover/07.jpg","captions":"Manoj - Rajeshwari","album": "manoj"},
  {"albumcategory":"wedding","photo":"http://www.shivuweddingphotography.com/uploads/albumcover/JE0A1128.jpg","captions":"Jahnavi","album": "jahnavi"},
  {"albumcategory":"wedding","photo":"http://www.shivuweddingphotography.com/uploads/albumcover/02.jpg","captions":"Jyothi - Rudresh","album": "rudresh"},
  {"albumcategory":"wedding","photo":"http://www.shivuweddingphotography.com/uploads/albumcover/IMG_2933 copy.jpg","captions":"Kavya - Sharath","album": "kavya"},
  {"albumcategory":"wedding","photo":"http://www.shivuweddingphotography.com/uploads/albumcover/104.jpg","captions":"Kausalya","album": "kausalya"},
  {"albumcategory":"wedding","photo":"http://www.shivuweddingphotography.com/uploads/albumcover/06.jpg","captions":"Dharshana - Siddha`rth","album": "dhar"},
  {"albumcategory":"wedding","photo":"http://www.shivuweddingphotography.com/uploads/albumcover/403.jpg","captions":"Neha - Navneeth (Hubballi)","album": "neha"},
  {"albumcategory":"wedding","photo":"http://www.shivuweddingphotography.com/uploads/albumcover/11.jpg","captions":"Rakesh","album": "rakesh"},
  {"albumcategory":"wedding","photo":"http://www.shivuweddingphotography.com/uploads/albumcover/IMG_9805.jpg","captions":"Rashmi - Santhosh","album": "rashmi"},
  {"albumcategory":"wedding","photo":"http://www.shivuweddingphotography.com/uploads/albumcover/IMG_5707 copy.jpg","captions":"Vidya - Pramod","album": "vpramod"},
  {"albumcategory":"wedding","photo":"http://www.shivuweddingphotography.com/uploads/albumcover/VSL_8923.jpg","captions":"Uday Mantur","album": "udayam"},
  {"albumcategory":"wedding","photo":"http://www.shivuweddingphotography.com/uploads/albumcover/JE0A1112.jpg","captions":"Swathi wedding","album": "swathiw"},
  {"albumcategory":"wedding","photo":"http://www.shivuweddingphotography.com/uploads/albumcover/JE0A7219.jpg","captions":"Sahana Vijaykumar","album": "sahanav"},
  {"albumcategory":"wedding","photo":"http://www.shivuweddingphotography.com/uploads/albumcover/JE0A3484.jpg","captions":"Shilpa Santhosh","album": "shilpasan"},
  {"albumcategory":"wedding","photo":"http://www.shivuweddingphotography.com/uploads/albumcover/59.jpg","captions":"Dr.Raj Hemanth - Dr.Savitha","album": "drraj"},
  {"albumcategory":"engagementshots","photo":"http://www.shivuweddingphotography.com/uploads/albumcover/img_1027.jpg","captions":"Samarth - Nisha","album": "samarth"},
  {"albumcategory":"engagementshots","photo":"http://www.shivuweddingphotography.com/uploads/albumcover/003.jpg","captions":"Meghana","album": "meghana"},
  {"albumcategory":"engagementshots","photo":"http://www.shivuweddingphotography.com/uploads/albumcover/_D819287 copy.jpg","captions":"Rashmi - Santhosh","album": "rashmis"},
  {"albumcategory":"prepostwedding","photo":"http://www.shivuweddingphotography.com/uploads/albumcover/l1 (10).jpg","captions":"Lavanya - Madhu","album": "lavanyam"},
  {"albumcategory":"prepostwedding","photo":"http://www.shivuweddingphotography.com/uploads/albumcover/_D810366 copy.jpg","captions":"Rashmi - Santhosh","album": "srashmi"},
  {"albumcategory":"prepostwedding","photo":"http://www.shivuweddingphotography.com/uploads/albumcover/03.jpg","captions":"Nandini - Shivaprakash","album": "nandini"},
  {"albumcategory":"pregnancy","photo":"http://www.shivuweddingphotography.com/uploads/albumcover/JE0A8685.jpg","captions":"Mamatha Seemantha","album":"mamathas"},
  {"albumcategory":"pregnancy","photo":"http://www.shivuweddingphotography.com/uploads/albumcover/105.jpg","captions":"Divya Nagesh","album": "divyan"},
  {"albumcategory":"pregnancy","photo":"http://www.shivuweddingphotography.com/uploads/albumcover/JE0A0604.jpg","captions":"Mamatha Guru","album": "mamathag"},
  {"albumcategory":"pregnancy","photo":"http://www.shivuweddingphotography.com/uploads/albumcover/JE0A6771.jpg","captions":"Nandini Shivaprakash","album": "nandinis"},
  {"albumcategory":"baby","photo":"http://www.shivuweddingphotography.com/uploads/albumcover/013.jpg","captions":"Driti","album": "drithi"},
  {"albumcategory":"kids","photo":"http://www.shivuweddingphotography.com/uploads/albumcover/20111126582946423.jpg","captions":"Shanmukh birthday","album": "shankmukh"},
  {"albumcategory":"kids","photo":"http://www.shivuweddingphotography.com/uploads/albumcover/s013.jpg","captions":"Arjun Upanayana","album": "arjunu"},
  {"albumcategory":"kids","photo":"http://www.shivuweddingphotography.com/uploads/albumcover/JE0A1353-Low.jpg","captions":"Avinash Upanayana","album": "avinashu"},
  {"albumcategory":"kids","photo":"http://www.shivuweddingphotography.com/uploads/albumcover/_D810808.jpg","captions":"Vedapriya birthday","album": "vedapriya"},
  {"albumcategory":"kids","photo":"http://www.shivuweddingphotography.com/uploads/albumcover/JE0A5476.jpg","captions":"Kids photos","album": "kidss"},
  {"albumcategory":"kids","photo":"http://www.shivuweddingphotography.com/uploads/albumcover/_D817669.jpg","captions":"Sara birthday","album": "sara"},
  {"albumcategory":"kids","photo":"http://www.shivuweddingphotography.com/uploads/albumcover/JE0A6536.jpg","captions":"Vedavyas birthday","album": "vedavyas"},
  {"albumcategory":"events","photo":"http://www.shivuweddingphotography.com/uploads/albumcover/endumareyadahaadu.jpg","captions":"Endu Mareyada Haadu - Ravi Belagere","album": "emh"},
  {"albumcategory":"events","photo":"http://www.shivuweddingphotography.com/uploads/albumcover/chaaranamusicnight.jpg","captions":"Chaarana Music Night","album": "cmn"},
  {"albumcategory":"events","photo":"http://www.shivuweddingphotography.com/uploads/albumcover/kannadanamana.jpg","captions":"Kannada Namana - Ravi Belagere","album": "knm"},
  {"albumcategory":"events","photo":"http://www.shivuweddingphotography.com/uploads/albumcover/thatanthaheli.jpg","captions":"That Antha Heli - 2500 episode ","album": "tah"},
  {"albumcategory":"events","photo":"http://www.shivuweddingphotography.com/uploads/albumcover/_MG_6133.jpg","captions":"Sumukhchand Music Concert","album": "smc"},
  {"albumcategory":"events","photo":"http://www.shivuweddingphotography.com/uploads/albumcover/ravibelaggare-emhaddu.jpg","captions":"Ravi Belagere in Endu Mareyada Haadu","album": "rbe"},
  {"albumcategory":"events","photo":"http://www.shivuweddingphotography.com/uploads/albumcover/kannadanamana_etv.jpg","captions":"Kannada Namana ETV","album": "kne"},
  {"albumcategory":"events","photo":"http://www.shivuweddingphotography.com/uploads/albumcover/JE0A3066.jpg","captions":"Family Photography","album": "family"},
  {"albumcategory":"events","photo":"http://www.shivuweddingphotography.com/uploads/albumcover/IMG_9386.jpg","captions":"Taj Vivanta","album": "taj"}
]
